metrx/__init__.py
metrx/distance_measures.py
metrx/statistical_measures.py
metrx/utils.py
metrx-0.1.0.dist-info/LICENSE
metrx-0.1.0.dist-info/METADATA
metrx-0.1.0.dist-info/WHEEL
metrx-0.1.0.dist-info/top_level.txt
metrx-0.1.0.dist-info/RECORD
