Metadata-Version: 2.1
Name: metrx
Version: 0.1.0
Summary: "A library containing a collection of distance and similarity measures to compare time series data."
Author-email: Kay Pompetzki <kay.hansel@tu-darmstadt.de>, Theo Gruner <theo_sunao.gruner@tu-darmstadt.de>, Firas Al-Hafez <fi.alhafez@gmail.com>
License: MIT License
Project-URL: Homepage, https://github.com/pompetzki/metrx
Project-URL: Repository, https://github.com/pompetzki/metrx
Project-URL: Issues, https://github.com/pompetzki/metrx/issues
Keywords: Distance Measures,Statistical Measures,jax
Classifier: Programming Language :: Python :: 3
Classifier: License :: OSI Approved :: MIT License
Classifier: Operating System :: OS Independent
Requires-Python: >=3.10
License-File: LICENSE
Requires-Dist: distrax>=0.1.5
Requires-Dist: flax>=0.8.1
Requires-Dist: jax>=0.4.25
Requires-Dist: optax>=0.1.7
Requires-Dist: ott-jax>=0.4.9
Requires-Dist: numpy
Requires-Dist: pytest
